[
  {
    "PlateNumb": "FAB-229",
    "StopUID": "THB188119",
    "StopID": "188119",
    "StopName": {
      "Zh_tw": "臺北科技大學(忠孝)",
      "En": "National Taipei University of Technology(Zhongxiao)"
    },
    "RouteUID": "THB1815",
    "RouteID": "1815",
    "RouteName": {
      "Zh_tw": "1815",
      "En": "1815"
    },
    "SubRouteUID": "THB181502",
    "SubRouteID": "181502",
    "SubRouteName": {
      "Zh_tw": "1815",
      "En": "1815"
    },
    "Direction": 1,
    "EstimateTime": 59,
    "StopCountDown": 1,
    "CurrentStop": "269623",
    "DestinationStop": "300516",
    "StopSequence": 56,
    "StopStatus": 0,
    "MessageType": 2,
    "IsLastBus": true,
    "DataTime": "2025-05-24T22:33:49+08:00",
    "SrcTransTime": "2025-05-24T22:35:49+08:00",
    "UpdateTime": "2025-05-24T22:35:51+08:00"
  },
  {
    "PlateNumb": "-1",
    "StopUID": "THB188119",
    "StopID": "188119",
    "StopName": {
      "Zh_tw": "臺北科技大學(忠孝)",
      "En": "National Taipei University of Technology(Zhongxiao)"
    },
    "RouteUID": "THB1815",
    "RouteID": "1815",
    "RouteName": {
      "Zh_tw": "1815",
      "En": "1815"
    },
    "SubRouteUID": "THB1815A2",
    "SubRouteID": "1815A2",
    "SubRouteName": {
      "Zh_tw": "1815A",
      "En": "1815A"
    },
    "Direction": 1,
    "StopCountDown": 0,
    "CurrentStop": "-1",
    "DestinationStop": "300516",
    "StopSequence": 59,
    "StopStatus": 3,
    "MessageType": 2,
    "IsLastBus": true,
    "DataTime": "2025-05-24T22:35:47+08:00",
    "SrcTransTime": "2025-05-24T22:35:49+08:00",
    "UpdateTime": "2025-05-24T22:35:51+08:00"
  },
  {
    "PlateNumb": "-1",
    "StopUID": "THB188119",
    "StopID": "188119",
    "StopName": {
      "Zh_tw": "臺北科技大學(忠孝)",
      "En": "National Taipei University of Technology(Zhongxiao)"
    },
    "RouteUID": "THB1815",
    "RouteID": "1815",
    "RouteName": {
      "Zh_tw": "1815",
      "En": "1815"
    },
    "SubRouteUID": "THB1815C2",
    "SubRouteID": "1815C2",
    "SubRouteName": {
      "Zh_tw": "1815C",
      "En": "1815C"
    },
    "Direction": 1,
    "StopCountDown": 0,
    "CurrentStop": "-1",
    "DestinationStop": "300516",
    "StopSequence": 47,
    "StopStatus": 4,
    "MessageType": 2,
    "IsLastBus": false,
    "DataTime": "2025-05-24T22:35:47+08:00",
    "SrcTransTime": "2025-05-24T22:35:49+08:00",
    "UpdateTime": "2025-05-24T22:35:51+08:00"
  },
  {
    "PlateNumb": "-1",
    "StopUID": "THB188119",
    "StopID": "188119",
    "StopName": {
      "Zh_tw": "臺北科技大學(忠孝)",
      "En": "National Taipei University of Technology(Zhongxiao)"
    },
    "RouteUID": "THB1815",
    "RouteID": "1815",
    "RouteName": {
      "Zh_tw": "1815",
      "En": "1815"
    },
    "SubRouteUID": "THB1815D2",
    "SubRouteID": "1815D2",
    "SubRouteName": {
      "Zh_tw": "1815D",
      "En": "1815D"
    },
    "Direction": 1,
    "StopCountDown": 0,
    "CurrentStop": "-1",
    "DestinationStop": "300516",
    "StopSequence": 32,
    "StopStatus": 3,
    "MessageType": 2,
    "IsLastBus": true,
    "DataTime": "2025-05-24T22:35:47+08:00",
    "SrcTransTime": "2025-05-24T22:35:49+08:00",
    "UpdateTime": "2025-05-24T22:35:51+08:00"
  },
  {
    "PlateNumb": "-1",
    "StopUID": "THB188119",
    "StopID": "188119",
    "StopName": {
      "Zh_tw": "臺北科技大學(忠孝)",
      "En": "National Taipei University of Technology(Zhongxiao)"
    },
    "RouteUID": "THB1815",
    "RouteID": "1815",
    "RouteName": {
      "Zh_tw": "1815",
      "En": "1815"
    },
    "SubRouteUID": "THB1815E2",
    "SubRouteID": "1815E2",
    "SubRouteName": {
      "Zh_tw": "1815E",
      "En": "1815E"
    },
    "Direction": 1,
    "StopCountDown": 0,
    "CurrentStop": "-1",
    "DestinationStop": "300516",
    "StopSequence": 60,
    "StopStatus": 3,
    "MessageType": 2,
    "IsLastBus": true,
    "DataTime": "2025-05-24T22:35:47+08:00",
    "SrcTransTime": "2025-05-24T22:35:49+08:00",
    "UpdateTime": "2025-05-24T22:35:51+08:00"
  },
  {
    "PlateNumb": "101-U7",
    "StopUID": "THB254899",
    "StopID": "254899",
    "StopName": {
      "Zh_tw": "景美里",
      "En": "Jingmei Village"
    },
    "RouteUID": "THB1815",
    "RouteID": "1815",
    "RouteName": {
      "Zh_tw": "1815",
      "En": "1815"
    },
    "SubRouteUID": "THB181501",
    "SubRouteID": "181501",
    "SubRouteName": {
      "Zh_tw": "1815",
      "En": "1815"
    },
    "Direction": 0,
    "EstimateTime": 350,
    "StopCountDown": 6,
    "CurrentStop": "270668",
    "DestinationStop": "269906",
    "StopSequence": 33,
    "StopStatus": 0,
    "MessageType": 2,
    "IsLastBus": false,
    "DataTime": "2025-05-24T22:35:16+08:00",
    "SrcTransTime": "2025-05-24T22:35:49+08:00",
    "UpdateTime": "2025-05-24T22:35:51+08:00"
  },
  {
    "PlateNumb": "-1",
    "StopUID": "THB254899",
    "StopID": "254899",
    "StopName": {
      "Zh_tw": "景美里",
      "En": "Jingmei Village"
    },
    "RouteUID": "THB1815",
    "RouteID": "1815",
    "RouteName": {
      "Zh_tw": "1815",
      "En": "1815"
    },
    "SubRouteUID": "THB1815A1",
    "SubRouteID": "1815A1",
    "SubRouteName": {
      "Zh_tw": "1815A",
      "En": "1815A"
    },
    "Direction": 0,
    "StopCountDown": 0,
    "CurrentStop": "-1",
    "DestinationStop": "271293",
    "StopSequence": 33,
    "StopStatus": 3,
    "MessageType": 2,
    "IsLastBus": true,
    "DataTime": "2025-05-24T22:35:47+08:00",
    "SrcTransTime": "2025-05-24T22:35:49+08:00",
    "UpdateTime": "2025-05-24T22:35:51+08:00"
  },
  {
    "PlateNumb": "-1",
    "StopUID": "THB254899",
    "StopID": "254899",
    "StopName": {
      "Zh_tw": "景美里",
      "En": "Jingmei Village"
    },
    "RouteUID": "THB1815",
    "RouteID": "1815",
    "RouteName": {
      "Zh_tw": "1815",
      "En": "1815"
    },
    "SubRouteUID": "THB1815B1",
    "SubRouteID": "1815B1",
    "SubRouteName": {
      "Zh_tw": "1815B",
      "En": "1815B"
    },
    "Direction": 0,
    "StopCountDown": 0,
    "CurrentStop": "-1",
    "DestinationStop": "269906",
    "StopSequence": 34,
    "StopStatus": 4,
    "MessageType": 2,
    "IsLastBus": false,
    "DataTime": "2025-05-24T22:35:47+08:00",
    "SrcTransTime": "2025-05-24T22:35:49+08:00",
    "UpdateTime": "2025-05-24T22:35:51+08:00"
  },
  {
    "PlateNumb": "-1",
    "StopUID": "THB254899",
    "StopID": "254899",
    "StopName": {
      "Zh_tw": "景美里",
      "En": "Jingmei Village"
    },
    "RouteUID": "THB1815",
    "RouteID": "1815",
    "RouteName": {
      "Zh_tw": "1815",
      "En": "1815"
    },
    "SubRouteUID": "THB1815C1",
    "SubRouteID": "1815C1",
    "SubRouteName": {
      "Zh_tw": "1815C",
      "En": "1815C"
    },
    "Direction": 0,
    "StopCountDown": 0,
    "CurrentStop": "-1",
    "DestinationStop": "269906",
    "StopSequence": 23,
    "StopStatus": 4,
    "MessageType": 2,
    "IsLastBus": false,
    "DataTime": "2025-05-24T22:35:47+08:00",
    "SrcTransTime": "2025-05-24T22:35:49+08:00",
    "UpdateTime": "2025-05-24T22:35:51+08:00"
  },
  {
    "PlateNumb": "FAB-219",
    "StopUID": "THB254899",
    "StopID": "254899",
    "StopName": {
      "Zh_tw": "景美里",
      "En": "Jingmei Village"
    },
    "RouteUID": "THB1815",
    "RouteID": "1815",
    "RouteName": {
      "Zh_tw": "1815",
      "En": "1815"
    },
    "SubRouteUID": "THB1815D1",
    "SubRouteID": "1815D1",
    "SubRouteName": {
      "Zh_tw": "1815D",
      "En": "1815D"
    },
    "Direction": 0,
    "EstimateTime": 3523,
    "StopCountDown": 27,
    "CurrentStop": "284384",
    "DestinationStop": "270102",
    "StopSequence": 33,
    "StopStatus": 0,
    "MessageType": 2,
    "IsLastBus": true,
    "DataTime": "2025-05-24T22:35:24+08:00",
    "SrcTransTime": "2025-05-24T22:35:49+08:00",
    "UpdateTime": "2025-05-24T22:35:51+08:00"
  },
  {
    "PlateNumb": "-1",
    "StopUID": "THB254899",
    "StopID": "254899",
    "StopName": {
      "Zh_tw": "景美里",
      "En": "Jingmei Village"
    },
    "RouteUID": "THB1815",
    "RouteID": "1815",
    "RouteName": {
      "Zh_tw": "1815",
      "En": "1815"
    },
    "SubRouteUID": "THB1815E1",
    "SubRouteID": "1815E1",
    "SubRouteName": {
      "Zh_tw": "1815E",
      "En": "1815E"
    },
    "Direction": 0,
    "StopCountDown": 0,
    "CurrentStop": "-1",
    "DestinationStop": "307464",
    "StopSequence": 33,
    "StopStatus": 3,
    "MessageType": 2,
    "IsLastBus": true,
    "DataTime": "2025-05-24T22:35:47+08:00",
    "SrcTransTime": "2025-05-24T22:35:49+08:00",
    "UpdateTime": "2025-05-24T22:35:51+08:00"
  },
  {
    "PlateNumb": "249-U5",
    "StopUID": "THB255394",
    "StopID": "255394",
    "StopName": {
      "Zh_tw": "情人湖路口",
      "En": "Qingrenhu intersection"
    },
    "RouteUID": "THB1815",
    "RouteID": "1815",
    "RouteName": {
      "Zh_tw": "1815",
      "En": "1815"
    },
    "SubRouteUID": "THB181502",
    "SubRouteID": "181502",
    "SubRouteName": {
      "Zh_tw": "1815",
      "En": "1815"
    },
    "Direction": 1,
    "EstimateTime": 1063,
    "StopCountDown": 19,
    "CurrentStop": "269476",
    "DestinationStop": "300516",
    "StopSequence": 38,
    "StopStatus": 0,
    "MessageType": 2,
    "IsLastBus": true,
    "DataTime": "2025-05-24T22:34:58+08:00",
    "SrcTransTime": "2025-05-24T22:35:49+08:00",
    "UpdateTime": "2025-05-24T22:35:51+08:00"
  },
  {
    "PlateNumb": "-1",
    "StopUID": "THB255394",
    "StopID": "255394",
    "StopName": {
      "Zh_tw": "情人湖路口",
      "En": "Qingrenhu intersection"
    },
    "RouteUID": "THB1815",
    "RouteID": "1815",
    "RouteName": {
      "Zh_tw": "1815",
      "En": "1815"
    },
    "SubRouteUID": "THB1815A2",
    "SubRouteID": "1815A2",
    "SubRouteName": {
      "Zh_tw": "1815A",
      "En": "1815A"
    },
    "Direction": 1,
    "StopCountDown": 0,
    "CurrentStop": "-1",
    "DestinationStop": "300516",
    "StopSequence": 41,
    "StopStatus": 3,
    "MessageType": 2,
    "IsLastBus": true,
    "DataTime": "2025-05-24T22:35:47+08:00",
    "SrcTransTime": "2025-05-24T22:35:49+08:00",
    "UpdateTime": "2025-05-24T22:35:51+08:00"
  },
  {
    "PlateNumb": "-1",
    "StopUID": "THB255394",
    "StopID": "255394",
    "StopName": {
      "Zh_tw": "情人湖路口",
      "En": "Qingrenhu intersection"
    },
    "RouteUID": "THB1815",
    "RouteID": "1815",
    "RouteName": {
      "Zh_tw": "1815",
      "En": "1815"
    },
    "SubRouteUID": "THB1815B2",
    "SubRouteID": "1815B2",
    "SubRouteName": {
      "Zh_tw": "1815B",
      "En": "1815B"
    },
    "Direction": 1,
    "StopCountDown": 0,
    "CurrentStop": "-1",
    "DestinationStop": "285633",
    "StopSequence": 38,
    "StopStatus": 4,
    "MessageType": 2,
    "IsLastBus": false,
    "DataTime": "2025-05-24T22:35:47+08:00",
    "SrcTransTime": "2025-05-24T22:35:49+08:00",
    "UpdateTime": "2025-05-24T22:35:51+08:00"
  },
  {
    "PlateNumb": "-1",
    "StopUID": "THB255394",
    "StopID": "255394",
    "StopName": {
      "Zh_tw": "情人湖路口",
      "En": "Qingrenhu intersection"
    },
    "RouteUID": "THB1815",
    "RouteID": "1815",
    "RouteName": {
      "Zh_tw": "1815",
      "En": "1815"
    },
    "SubRouteUID": "THB1815C2",
    "SubRouteID": "1815C2",
    "SubRouteName": {
      "Zh_tw": "1815C",
      "En": "1815C"
    },
    "Direction": 1,
    "StopCountDown": 0,
    "CurrentStop": "-1",
    "DestinationStop": "300516",
    "StopSequence": 38,
    "StopStatus": 4,
    "MessageType": 2,
    "IsLastBus": false,
    "DataTime": "2025-05-24T22:35:47+08:00",
    "SrcTransTime": "2025-05-24T22:35:49+08:00",
    "UpdateTime": "2025-05-24T22:35:51+08:00"
  },
  {
    "PlateNumb": "-1",
    "StopUID": "THB255394",
    "StopID": "255394",
    "StopName": {
      "Zh_tw": "情人湖路口",
      "En": "Qingrenhu intersection"
    },
    "RouteUID": "THB1815",
    "RouteID": "1815",
    "RouteName": {
      "Zh_tw": "1815",
      "En": "1815"
    },
    "SubRouteUID": "THB1815D2",
    "SubRouteID": "1815D2",
    "SubRouteName": {
      "Zh_tw": "1815D",
      "En": "1815D"
    },
    "Direction": 1,
    "StopCountDown": 0,
    "CurrentStop": "-1",
    "DestinationStop": "300516",
    "StopSequence": 14,
    "StopStatus": 3,
    "MessageType": 2,
    "IsLastBus": true,
    "DataTime": "2025-05-24T22:35:47+08:00",
    "SrcTransTime": "2025-05-24T22:35:49+08:00",
    "UpdateTime": "2025-05-24T22:35:51+08:00"
  },
  {
    "PlateNumb": "-1",
    "StopUID": "THB255394",
    "StopID": "255394",
    "StopName": {
      "Zh_tw": "情人湖路口",
      "En": "Qingrenhu intersection"
    },
    "RouteUID": "THB1815",
    "RouteID": "1815",
    "RouteName": {
      "Zh_tw": "1815",
      "En": "1815"
    },
    "SubRouteUID": "THB1815E2",
    "SubRouteID": "1815E2",
    "SubRouteName": {
      "Zh_tw": "1815E",
      "En": "1815E"
    },
    "Direction": 1,
    "StopCountDown": 0,
    "CurrentStop": "-1",
    "DestinationStop": "300516",
    "StopSequence": 42,
    "StopStatus": 3,
    "MessageType": 2,
    "IsLastBus": true,
    "DataTime": "2025-05-24T22:35:47+08:00",
    "SrcTransTime": "2025-05-24T22:35:49+08:00",
    "UpdateTime": "2025-05-24T22:35:51+08:00"
  },
  {
    "PlateNumb": "233-U5",
    "StopUID": "THB259045",
    "StopID": "259045",
    "StopName": {
      "Zh_tw": "情人湖路口",
      "En": "Qingrenhu intersection"
    },
    "RouteUID": "THB1815",
    "RouteID": "1815",
    "RouteName": {
      "Zh_tw": "1815",
      "En": "1815"
    },
    "SubRouteUID": "THB181501",
    "SubRouteID": "181501",
    "SubRouteName": {
      "Zh_tw": "1815",
      "En": "1815"
    },
    "Direction": 0,
    "EstimateTime": 177,
    "StopCountDown": 3,
    "CurrentStop": "270663",
    "DestinationStop": "269906",
    "StopSequence": 21,
    "StopStatus": 0,
    "MessageType": 2,
    "IsLastBus": false,
    "DataTime": "2025-05-24T22:35:06+08:00",
    "SrcTransTime": "2025-05-24T22:35:49+08:00",
    "UpdateTime": "2025-05-24T22:35:51+08:00"
  },
  {
    "PlateNumb": "-1",
    "StopUID": "THB259045",
    "StopID": "259045",
    "StopName": {
      "Zh_tw": "情人湖路口",
      "En": "Qingrenhu intersection"
    },
    "RouteUID": "THB1815",
    "RouteID": "1815",
    "RouteName": {
      "Zh_tw": "1815",
      "En": "1815"
    },
    "SubRouteUID": "THB1815A1",
    "SubRouteID": "1815A1",
    "SubRouteName": {
      "Zh_tw": "1815A",
      "En": "1815A"
    },
    "Direction": 0,
    "StopCountDown": 0,
    "CurrentStop": "-1",
    "DestinationStop": "271293",
    "StopSequence": 21,
    "StopStatus": 3,
    "MessageType": 2,
    "IsLastBus": true,
    "DataTime": "2025-05-24T22:35:47+08:00",
    "SrcTransTime": "2025-05-24T22:35:49+08:00",
    "UpdateTime": "2025-05-24T22:35:51+08:00"
  },
  {
    "PlateNumb": "-1",
    "StopUID": "THB259045",
    "StopID": "259045",
    "StopName": {
      "Zh_tw": "情人湖路口",
      "En": "Qingrenhu intersection"
    },
    "RouteUID": "THB1815",
    "RouteID": "1815",
    "RouteName": {
      "Zh_tw": "1815",
      "En": "1815"
    },
    "SubRouteUID": "THB1815B1",
    "SubRouteID": "1815B1",
    "SubRouteName": {
      "Zh_tw": "1815B",
      "En": "1815B"
    },
    "Direction": 0,
    "StopCountDown": 0,
    "CurrentStop": "-1",
    "DestinationStop": "269906",
    "StopSequence": 22,
    "StopStatus": 4,
    "MessageType": 2,
    "IsLastBus": false,
    "DataTime": "2025-05-24T22:35:47+08:00",
    "SrcTransTime": "2025-05-24T22:35:49+08:00",
    "UpdateTime": "2025-05-24T22:35:51+08:00"
  },
  {
    "PlateNumb": "-1",
    "StopUID": "THB259045",
    "StopID": "259045",
    "StopName": {
      "Zh_tw": "情人湖路口",
      "En": "Qingrenhu intersection"
    },
    "RouteUID": "THB1815",
    "RouteID": "1815",
    "RouteName": {
      "Zh_tw": "1815",
      "En": "1815"
    },
    "SubRouteUID": "THB1815C1",
    "SubRouteID": "1815C1",
    "SubRouteName": {
      "Zh_tw": "1815C",
      "En": "1815C"
    },
    "Direction": 0,
    "StopCountDown": 0,
    "CurrentStop": "-1",
    "DestinationStop": "269906",
    "StopSequence": 11,
    "StopStatus": 4,
    "MessageType": 2,
    "IsLastBus": false,
    "DataTime": "2025-05-24T22:35:47+08:00",
    "SrcTransTime": "2025-05-24T22:35:49+08:00",
    "UpdateTime": "2025-05-24T22:35:51+08:00"
  },
  {
    "PlateNumb": "FAB-219",
    "StopUID": "THB259045",
    "StopID": "259045",
    "StopName": {
      "Zh_tw": "情人湖路口",
      "En": "Qingrenhu intersection"
    },
    "RouteUID": "THB1815",
    "RouteID": "1815",
    "RouteName": {
      "Zh_tw": "1815",
      "En": "1815"
    },
    "SubRouteUID": "THB1815D1",
    "SubRouteID": "1815D1",
    "SubRouteName": {
      "Zh_tw": "1815D",
      "En": "1815D"
    },
    "Direction": 0,
    "EstimateTime": 2852,
    "StopCountDown": 15,
    "CurrentStop": "284384",
    "DestinationStop": "270102",
    "StopSequence": 21,
    "StopStatus": 0,
    "MessageType": 2,
    "IsLastBus": true,
    "DataTime": "2025-05-24T22:35:24+08:00",
    "SrcTransTime": "2025-05-24T22:35:49+08:00",
    "UpdateTime": "2025-05-24T22:35:51+08:00"
  },
  {
    "PlateNumb": "-1",
    "StopUID": "THB259045",
    "StopID": "259045",
    "StopName": {
      "Zh_tw": "情人湖路口",
      "En": "Qingrenhu intersection"
    },
    "RouteUID": "THB1815",
    "RouteID": "1815",
    "RouteName": {
      "Zh_tw": "1815",
      "En": "1815"
    },
    "SubRouteUID": "THB1815E1",
    "SubRouteID": "1815E1",
    "SubRouteName": {
      "Zh_tw": "1815E",
      "En": "1815E"
    },
    "Direction": 0,
    "StopCountDown": 0,
    "CurrentStop": "-1",
    "DestinationStop": "307464",
    "StopSequence": 21,
    "StopStatus": 3,
    "MessageType": 2,
    "IsLastBus": true,
    "DataTime": "2025-05-24T22:35:47+08:00",
    "SrcTransTime": "2025-05-24T22:35:49+08:00",
    "UpdateTime": "2025-05-24T22:35:51+08:00"
  },
  {
    "PlateNumb": "-1",
    "StopUID": "THB259987",
    "StopID": "259987",
    "StopName": {
      "Zh_tw": "金山中學",
      "En": "Jinshan High School"
    },
    "RouteUID": "THB1815",
    "RouteID": "1815",
    "RouteName": {
      "Zh_tw": "1815",
      "En": "1815"
    },
    "SubRouteUID": "THB181502",
    "SubRouteID": "181502",
    "SubRouteName": {
      "Zh_tw": "1815",
      "En": "1815"
    },
    "Direction": 1,
    "StopCountDown": 0,
    "CurrentStop": "-1",
    "DestinationStop": "300516",
    "StopSequence": 6,
    "StopStatus": 3,
    "MessageType": 2,
    "IsLastBus": true,
    "DataTime": "2025-05-24T22:35:47+08:00",
    "SrcTransTime": "2025-05-24T22:35:49+08:00",
    "UpdateTime": "2025-05-24T22:35:51+08:00"
  },
  {
    "PlateNumb": "-1",
    "StopUID": "THB259987",
    "StopID": "259987",
    "StopName": {
      "Zh_tw": "金山中學",
      "En": "Jinshan High School"
    },
    "RouteUID": "THB1815",
    "RouteID": "1815",
    "RouteName": {
      "Zh_tw": "1815",
      "En": "1815"
    },
    "SubRouteUID": "THB1815A2",
    "SubRouteID": "1815A2",
    "SubRouteName": {
      "Zh_tw": "1815A",
      "En": "1815A"
    },
    "Direction": 1,
    "StopCountDown": 0,
    "CurrentStop": "-1",
    "DestinationStop": "300516",
    "StopSequence": 9,
    "StopStatus": 3,
    "MessageType": 2,
    "IsLastBus": true,
    "DataTime": "2025-05-24T22:35:47+08:00",
    "SrcTransTime": "2025-05-24T22:35:49+08:00",
    "UpdateTime": "2025-05-24T22:35:51+08:00"
  },
  {
    "PlateNumb": "-1",
    "StopUID": "THB259987",
    "StopID": "259987",
    "StopName": {
      "Zh_tw": "金山中學",
      "En": "Jinshan High School"
    },
    "RouteUID": "THB1815",
    "RouteID": "1815",
    "RouteName": {
      "Zh_tw": "1815",
      "En": "1815"
    },
    "SubRouteUID": "THB1815B2",
    "SubRouteID": "1815B2",
    "SubRouteName": {
      "Zh_tw": "1815B",
      "En": "1815B"
    },
    "Direction": 1,
    "StopCountDown": 0,
    "CurrentStop": "-1",
    "DestinationStop": "285633",
    "StopSequence": 6,
    "StopStatus": 4,
    "MessageType": 2,
    "IsLastBus": false,
    "DataTime": "2025-05-24T22:35:47+08:00",
    "SrcTransTime": "2025-05-24T22:35:49+08:00",
    "UpdateTime": "2025-05-24T22:35:51+08:00"
  },
  {
    "PlateNumb": "-1",
    "StopUID": "THB259987",
    "StopID": "259987",
    "StopName": {
      "Zh_tw": "金山中學",
      "En": "Jinshan High School"
    },
    "RouteUID": "THB1815",
    "RouteID": "1815",
    "RouteName": {
      "Zh_tw": "1815",
      "En": "1815"
    },
    "SubRouteUID": "THB1815C2",
    "SubRouteID": "1815C2",
    "SubRouteName": {
      "Zh_tw": "1815C",
      "En": "1815C"
    },
    "Direction": 1,
    "StopCountDown": 0,
    "CurrentStop": "-1",
    "DestinationStop": "300516",
    "StopSequence": 6,
    "StopStatus": 4,
    "MessageType": 2,
    "IsLastBus": false,
    "DataTime": "2025-05-24T22:35:47+08:00",
    "SrcTransTime": "2025-05-24T22:35:49+08:00",
    "UpdateTime": "2025-05-24T22:35:51+08:00"
  },
  {
    "PlateNumb": "-1",
    "StopUID": "THB259987",
    "StopID": "259987",
    "StopName": {
      "Zh_tw": "金山中學",
      "En": "Jinshan High School"
    },
    "RouteUID": "THB1815",
    "RouteID": "1815",
    "RouteName": {
      "Zh_tw": "1815",
      "En": "1815"
    },
    "SubRouteUID": "THB1815E2",
    "SubRouteID": "1815E2",
    "SubRouteName": {
      "Zh_tw": "1815E",
      "En": "1815E"
    },
    "Direction": 1,
    "StopCountDown": 0,
    "CurrentStop": "-1",
    "DestinationStop": "300516",
    "StopSequence": 10,
    "StopStatus": 3,
    "MessageType": 2,
    "IsLastBus": true,
    "DataTime": "2025-05-24T22:35:47+08:00",
    "SrcTransTime": "2025-05-24T22:35:49+08:00",
    "UpdateTime": "2025-05-24T22:35:51+08:00"
  },
  {
    "PlateNumb": "FAB-081",
    "StopUID": "THB260653",
    "StopID": "260653",
    "StopName": {
      "Zh_tw": "捷運忠孝復興站",
      "En": "MRT Zhongxiao Fuxing Station"
    },
    "RouteUID": "THB1815",
    "RouteID": "1815",
    "RouteName": {
      "Zh_tw": "1815",
      "En": "1815"
    },
    "SubRouteUID": "THB181502",
    "SubRouteID": "181502",
    "SubRouteName": {
      "Zh_tw": "1815",
      "En": "1815"
    },
    "Direction": 1,
    "EstimateTime": 291,
    "StopCountDown": 2,
    "CurrentStop": "268091",
    "DestinationStop": "300516",
    "StopSequence": 54,
    "StopStatus": 0,
    "MessageType": 2,
    "IsLastBus": true,
    "DataTime": "2025-05-24T22:34:09+08:00",
    "SrcTransTime": "2025-05-24T22:35:49+08:00",
    "UpdateTime": "2025-05-24T22:35:51+08:00"
  },
  {
    "PlateNumb": "-1",
    "StopUID": "THB260653",
    "StopID": "260653",
    "StopName": {
      "Zh_tw": "捷運忠孝復興站",
      "En": "MRT Zhongxiao Fuxing Station"
    },
    "RouteUID": "THB1815",
    "RouteID": "1815",
    "RouteName": {
      "Zh_tw": "1815",
      "En": "1815"
    },
    "SubRouteUID": "THB1815A2",
    "SubRouteID": "1815A2",
    "SubRouteName": {
      "Zh_tw": "1815A",
      "En": "1815A"
    },
    "Direction": 1,
    "StopCountDown": 0,
    "CurrentStop": "-1",
    "DestinationStop": "300516",
    "StopSequence": 57,
    "StopStatus": 3,
    "MessageType": 2,
    "IsLastBus": true,
    "DataTime": "2025-05-24T22:35:47+08:00",
    "SrcTransTime": "2025-05-24T22:35:49+08:00",
    "UpdateTime": "2025-05-24T22:35:51+08:00"
  }
]